vgis_encrption/__init__.py
vgis_encrption/encrptionTools.py
vgis_encrption-1.0.3.dist-info/METADATA
vgis_encrption-1.0.3.dist-info/WHEEL
vgis_encrption-1.0.3.dist-info/top_level.txt
vgis_encrption-1.0.3.dist-info/RECORD
